monocle_yandexmap/widgets.py
monocle_yandexmap/__init__.py
monocle_yandexmap/models.py
monocle_yandexmap/monocle.py
monocle_yandexmap/admin.py
monocle_yandexmap/templates/monocle_yandexmap/monocle_yandexmap.html
monocle_yandexmap/fixtures/monocle_yandexmap.json
monocle_yandexmap/fixtures/monocle_yandexmap/marker.ico
monocle_yandexmap/static/monocle_yandexmap/monocle_yandexmap.js
monocle_yandexmap/static/monocle_yandexmap/monocle_yandexmap_admin.js
monocle_yandexmap/static/monocle_yandexmap/monocle_yandexmap_admin.css
monocle_yandexmap/static/monocle_yandexmap/monocle_yandexmap.css
monocle_yandexmap-0.0.4.dist-info/metadata.json
monocle_yandexmap-0.0.4.dist-info/WHEEL
monocle_yandexmap-0.0.4.dist-info/METADATA
monocle_yandexmap-0.0.4.dist-info/top_level.txt
monocle_yandexmap-0.0.4.dist-info/DESCRIPTION.rst
monocle_yandexmap-0.0.4.dist-info/RECORD
